TimeMurmur/Model.py
TimeMurmur/Murmur.py
TimeMurmur/Optimizer.py
TimeMurmur/__init__.py
TimeMurmur/basis_functions/FourierBasisFunction.py
TimeMurmur/basis_functions/LinearBasisFunction.py
TimeMurmur/basis_functions/__init__.py
TimeMurmur/builder/BuildArAxis.py
TimeMurmur/builder/BuildHierarchy.py
TimeMurmur/builder/BuildIdAxis.py
TimeMurmur/builder/BuildPanelAxis.py
TimeMurmur/builder/BuildTimeAxis.py
TimeMurmur/builder/Builder.py
TimeMurmur/builder/ExtractFeatures.py
TimeMurmur/builder/PreProcess.py
TimeMurmur/builder/Transformer.py
TimeMurmur/builder/__init__.py
TimeMurmur/utils/FeatureExtraction.py
TimeMurmur/utils/__init__.py
TimeMurmur/utils/series_utils.py
TimeMurmur/utils/utility_functions.py
TimeMurmur-0.1.3.dist-info/LICENSE
TimeMurmur-0.1.3.dist-info/METADATA
TimeMurmur-0.1.3.dist-info/WHEEL
TimeMurmur-0.1.3.dist-info/top_level.txt
TimeMurmur-0.1.3.dist-info/RECORD
